py_visual_algo/__init__.py
py_visual_algo/utils.py
py_visual_algo/algorithms/__init__.py
py_visual_algo/algorithms/evolutionary.py
py_visual_algo/algorithms/graph.py
py_visual_algo/algorithms/pathfinding.py
py_visual_algo/algorithms/searching.py
py_visual_algo/algorithms/sorting.py
py_visual_algo/algorithms/trees.py
py_visual_algo/algorithms/evolutionary/__init__.py
py_visual_algo/algorithms/evolutionary/ant_colony.py
py_visual_algo/algorithms/evolutionary/artificial_bee_colony.py
py_visual_algo/algorithms/evolutionary/cultural_algorithm.py
py_visual_algo/algorithms/evolutionary/differential_evolution.py
py_visual_algo/algorithms/evolutionary/genetic_algorithm.py
py_visual_algo/algorithms/evolutionary/harmony_search.py
py_visual_algo/algorithms/evolutionary/memetic_algorithm.py
py_visual_algo/algorithms/evolutionary/particle_swarm.py
py_visual_algo/algorithms/evolutionary/simulated_annealing.py
py_visual_algo/ui/__init__.py
py_visual_algo/ui/cli.py
py_visual_algo/ui/gui.py
py_visual_algo/visualizer/__init__.py
py_visual_algo/visualizer/exporter.py
py_visual_algo/visualizer/plotter.py
py_visual_algo/visualizer/themes.py
py_visual_algo-0.2.2.data/data/examples/a_star1.py
py_visual_algo-0.2.2.data/data/examples/ant_colony_optimization.py
py_visual_algo-0.2.2.data/data/examples/artificial_bee_colony.py
py_visual_algo-0.2.2.data/data/examples/bee.py
py_visual_algo-0.2.2.data/data/examples/bellman-ford_algorithm.py
py_visual_algo-0.2.2.data/data/examples/bfs1.py
py_visual_algo-0.2.2.data/data/examples/bfs2.py
py_visual_algo-0.2.2.data/data/examples/bfs_dfs.py
py_visual_algo-0.2.2.data/data/examples/bfs_with_edges.py
py_visual_algo-0.2.2.data/data/examples/binary_search.py
py_visual_algo-0.2.2.data/data/examples/bubble_sort1.py
py_visual_algo-0.2.2.data/data/examples/bubble_sort2.py
py_visual_algo-0.2.2.data/data/examples/cultural_algorithm.py
py_visual_algo-0.2.2.data/data/examples/dfs1.py
py_visual_algo-0.2.2.data/data/examples/dfs_with_edges.py
py_visual_algo-0.2.2.dist-info/LICENSE
py_visual_algo-0.2.2.dist-info/METADATA
py_visual_algo-0.2.2.dist-info/WHEEL
py_visual_algo-0.2.2.dist-info/entry_points.txt
py_visual_algo-0.2.2.dist-info/top_level.txt
py_visual_algo-0.2.2.dist-info/RECORD
