Metadata-Version: 2.1
Name: py-visual-algo
Version: 0.2.2
Summary: Interactive Algorithm Visualizer
Home-page: https://github.com/tirotir-ir/py_visual_algo
Author: DaryoushAlipour
Author-email: ai.tirotir@gmail.com
Project-URL: Bug Tracker, https://github.com/tirotir-ir/py_visual_algo/issues
Project-URL: Documentation, https://tirotir-ir.github.io/py_visual_algo
Project-URL: Source Code, https://github.com/tirotir-ir/py_visual_algo
Classifier: Programming Language :: Python :: 3
Classifier: License :: OSI Approved :: MIT License
Classifier: Operating System :: OS Independent
Classifier: Intended Audience :: Education
Classifier: Topic :: Software Development :: Libraries
Classifier: Topic :: Education
Requires-Python: >=3.7
License-File: LICENSE
Requires-Dist: matplotlib>=3.0.0
Requires-Dist: networkx>=2.5
Provides-Extra: dev
Requires-Dist: pytest>=6.0; extra == "dev"
Requires-Dist: flake8>=3.8; extra == "dev"
Requires-Dist: black>=22.0; extra == "dev"
Requires-Dist: pdoc>=12.0.0; extra == "dev"
